<annotation>
	<folder>images</folder>
	<filename>image11.jpg</filename>
	<path>/Users/peter/anaconda3/envs/ObjectDetectionTutorial/lib/python3.7/site-packages/tensorflow/models/research/object_detection/images/image11.jpg</path>
	<source>
		<database>Unknown</database>
	</source>
	<size>
		<width>240</width>
		<height>320</height>
		<depth>3</depth>
	</size>
	<segmented>0</segmented>
	<object>
		<name>one</name>
		<pose>Unspecified</pose>
		<truncated>0</truncated>
		<difficult>0</difficult>
		<bndbox>
			<xmin>127</xmin>
			<ymin>198</ymin>
			<xmax>163</xmax>
			<ymax>237</ymax>
		</bndbox>
	</object>
	<object>
		<name>one</name>
		<pose>Unspecified</pose>
		<truncated>0</truncated>
		<difficult>0</difficult>
		<bndbox>
			<xmin>97</xmin>
			<ymin>238</ymin>
			<xmax>135</xmax>
			<ymax>283</ymax>
		</bndbox>
	</object>
	<object>
		<name>two</name>
		<pose>Unspecified</pose>
		<truncated>0</truncated>
		<difficult>0</difficult>
		<bndbox>
			<xmin>127</xmin>
			<ymin>114</ymin>
			<xmax>163</xmax>
			<ymax>149</ymax>
		</bndbox>
	</object>
	<object>
		<name>two</name>
		<pose>Unspecified</pose>
		<truncated>0</truncated>
		<difficult>0</difficult>
		<bndbox>
			<xmin>9</xmin>
			<ymin>140</ymin>
			<xmax>52</xmax>
			<ymax>181</ymax>
		</bndbox>
	</object>
	<object>
		<name>three</name>
		<pose>Unspecified</pose>
		<truncated>0</truncated>
		<difficult>0</difficult>
		<bndbox>
			<xmin>41</xmin>
			<ymin>109</ymin>
			<xmax>84</xmax>
			<ymax>149</ymax>
		</bndbox>
	</object>
	<object>
		<name>four</name>
		<pose>Unspecified</pose>
		<truncated>0</truncated>
		<difficult>0</difficult>
		<bndbox>
			<xmin>72</xmin>
			<ymin>193</ymin>
			<xmax>104</xmax>
			<ymax>227</ymax>
		</bndbox>
	</object>
	<object>
		<name>five</name>
		<pose>Unspecified</pose>
		<truncated>0</truncated>
		<difficult>0</difficult>
		<bndbox>
			<xmin>184</xmin>
			<ymin>203</ymin>
			<xmax>226</xmax>
			<ymax>243</ymax>
		</bndbox>
	</object>
	<object>
		<name>five</name>
		<pose>Unspecified</pose>
		<truncated>0</truncated>
		<difficult>0</difficult>
		<bndbox>
			<xmin>182</xmin>
			<ymin>88</ymin>
			<xmax>224</xmax>
			<ymax>128</ymax>
		</bndbox>
	</object>
	<object>
		<name>six</name>
		<pose>Unspecified</pose>
		<truncated>0</truncated>
		<difficult>0</difficult>
		<bndbox>
			<xmin>158</xmin>
			<ymin>154</ymin>
			<xmax>200</xmax>
			<ymax>194</ymax>
		</bndbox>
	</object>
</annotation>
